{
  "items": [
    {
      "id": "uuid1",
      "categories": ["videogames"],
      "name": "Diablo 4",
      "picture": "uuid1.png"
    },
    {
      "id": "uuid2",
      "categories": ["BDs"],
      "name": "Elfe #10",
      "picture": "uuid2.png"
    },
    {
      "id": "uuid3",
      "categories": ["BDs"],
      "name": "Elfe #1",
      "picture": "https://www.bedetheque.com/media/Couvertures/Couv_182486.jpg",
      "owned": true
    },
    {
      "id": "uuid4",
      "categories": ["videogames", "Rpg"],
      "name": "Baldur's Gate 3",
      "picture": "https://m.media-amazon.com/images/M/MV5BMDFlY2MwZGQtZTVjYS00OTM2LWJjYWUtNGY1NjBhZGM0ZTljXkEyXkFqcGdeQXVyMTI0MzA4NTgw._V1_FMjpg_UX1000_.jpg"
    },
    {
      "id": "uuid5",
      "categories": ["videogames"],
      "name": "GTA 4",
      "picture": "https://upload.wikimedia.org/wikipedia/en/b/b7/Grand_Theft_Auto_IV_cover.jpg",
      "owned": true
    }
  ]
}
